sqlalchemyseed/__init__.py
sqlalchemyseed/attribute.py
sqlalchemyseed/constants.py
sqlalchemyseed/dynamic_seeder.py
sqlalchemyseed/errors.py
sqlalchemyseed/json.py
sqlalchemyseed/loader.py
sqlalchemyseed/seeder.py
sqlalchemyseed/util.py
sqlalchemyseed/validator.py
sqlalchemyseed/_future/__init__.py
sqlalchemyseed/_future/seeder.py
sqlalchemyseed-2.0.0.dist-info/LICENSE
sqlalchemyseed-2.0.0.dist-info/METADATA
sqlalchemyseed-2.0.0.dist-info/WHEEL
sqlalchemyseed-2.0.0.dist-info/top_level.txt
sqlalchemyseed-2.0.0.dist-info/RECORD
