Metadata-Version: 2.1
Name: sqlalchemyseed
Version: 2.0.0
Summary: SQLAlchemy Seeder
Home-page: https://github.com/jedymatt/sqlalchemyseed
Author: Jedy Matt Tabasco
Author-email: jedymatt@gmail.com
License: MIT
Project-URL: Documentation, https://sqlalchemyseed.readthedocs.io/
Project-URL: Source, https://github.com/jedymatt/sqlalchemyseed
Project-URL: Tracker, https://github.com/jedymatt/sqlalchemyseed/issues
Keywords: sqlalchemy,orm,seed,seeder,json,yaml
Classifier: License :: OSI Approved :: MIT License
Classifier: Programming Language :: Python :: 3.7
Classifier: Programming Language :: Python :: 3.8
Classifier: Programming Language :: Python :: 3.9
Classifier: Programming Language :: Python :: 3.10
Classifier: Programming Language :: Python :: 3.11
Requires-Python: >=3.7
License-File: LICENSE
Requires-Dist: SQLAlchemy (>=2.0)
Provides-Extra: yaml
Requires-Dist: PyYAML (>=5.4) ; extra == 'yaml'
